faare/__init__.py
faare/_version.py
faare/faare.py
faare/blender/blender_render_molecule.py
faare/settings/atom_colors.json
faare/settings/atom_radii.json
faare/settings/bonds.json
faare/settings/settings.json
faare-0.4.1.dist-info/METADATA
faare-0.4.1.dist-info/WHEEL
faare-0.4.1.dist-info/top_level.txt
faare-0.4.1.dist-info/RECORD
