Metadata-Version: 2.2
Name: faare
Version: 0.4.1
Summary: faare
Author-email: Ivo Filot <i.a.w.filot@tue.nl>
Maintainer-email: Ivo Filot <i.a.w.filot@tue.nl>
License: GPL-3.0-or-later
Project-URL: Homepage, https://gitlab.tue.nl/ifilot/faare
Project-URL: Bug Tracker, https://gitlab.tue.nl/ifilot/faare/-/issues
Classifier: Programming Language :: Python :: 3
Classifier: Operating System :: OS Independent
Requires-Python: >=3.9
Requires-Dist: numpy
Requires-Dist: ase
